totalopenstation/__init__.py
totalopenstation/formats/__init__.py
totalopenstation/formats/carlson_rw5.py
totalopenstation/formats/conversion.py
totalopenstation/formats/landxml.py
totalopenstation/formats/leica_gsi.py
totalopenstation/formats/leica_tcr_1205.py
totalopenstation/formats/leica_tcr_705.py
totalopenstation/formats/nikon_raw_v200.py
totalopenstation/formats/polar.py
totalopenstation/formats/sokkia_sdr33.py
totalopenstation/formats/topcon_gts.py
totalopenstation/formats/trimble_are.py
totalopenstation/formats/zeiss_r5.py
totalopenstation/formats/zeiss_rec_500.py
totalopenstation/models/__init__.py
totalopenstation/models/custom.py
totalopenstation/models/leica_tcr_1205.py
totalopenstation/models/leica_tcr_705.py
totalopenstation/models/nikon_npl_322plus.py
totalopenstation/models/nikon_npl_350.py
totalopenstation/models/topcon_gpt_3005.py
totalopenstation/models/trimble.py
totalopenstation/models/zeiss_elta_r55.py
totalopenstation/output/__init__.py
totalopenstation/output/tops_csv.py
totalopenstation/output/tops_dat.py
totalopenstation/output/tops_dxf.py
totalopenstation/output/tops_geojson.py
totalopenstation/output/tops_landxml.py
totalopenstation/output/tops_sql.py
totalopenstation/output/tops_txt.py
totalopenstation/tests/__init__.py
totalopenstation/tests/test_csv.py
totalopenstation/tests/test_dxf.py
totalopenstation/tests/test_geojson.py
totalopenstation/tests/test_landxml.py
totalopenstation/tests/test_leica_gsi.py
totalopenstation/tests/test_leica_tcr_1205.py
totalopenstation/tests/test_leica_tcr_705.py
totalopenstation/tests/test_nikon.py
totalopenstation/tests/test_polar.py
totalopenstation/tests/test_rw5.py
totalopenstation/tests/test_sokkia_sdr33.py
totalopenstation/tests/test_topcon_gts.py
totalopenstation/tests/test_trimble_are.py
totalopenstation/tests/test_zeiss.py
totalopenstation/tests/test_zeiss_r5.py
totalopenstation/utils/__init__.py
totalopenstation/utils/scanwin32.py
totalopenstation/utils/upref.py
totalopenstation-0.7.1.dist-info/licenses/AUTHORS
totalopenstation-0.7.1.dist-info/licenses/COPYING.txt
totalopenstation-0.7.1.dist-info/METADATA
totalopenstation-0.7.1.dist-info/WHEEL
totalopenstation-0.7.1.dist-info/entry_points.txt
totalopenstation-0.7.1.dist-info/top_level.txt
totalopenstation-0.7.1.dist-info/RECORD
