Metadata-Version: 2.4
Name: totalopenstation
Version: 0.7.1
Summary: Download and export survey data from your total station
Author: Stefano Costa, Damien Gaignon, Luca Bianconi
License-Expression: GPL-3.0
Project-URL: Homepage, https://tops.iosa.it/
Project-URL: Documentation, https://totalopenstation.readthedocs.io/
Project-URL: Repository, https://github.com/totalopenstation/totalopenstation.git
Project-URL: Issues, https://github.com/totalopenstation/totalopenstation/issues
Keywords: survey,geodimeter,fieldwork,format conversion
Classifier: Development Status :: 4 - Beta
Classifier: Environment :: Console
Classifier: Environment :: X11 Applications
Classifier: Intended Audience :: End Users/Desktop
Classifier: Operating System :: OS Independent
Classifier: Programming Language :: Python
Classifier: Programming Language :: Python :: 3 :: Only
Classifier: Programming Language :: Python :: 3.9
Classifier: Programming Language :: Python :: 3.10
Classifier: Programming Language :: Python :: 3.11
Classifier: Programming Language :: Python :: 3.12
Classifier: Programming Language :: Python :: 3.13
Classifier: Topic :: Scientific/Engineering :: GIS
Requires-Python: >=3.9
License-File: COPYING.txt
License-File: AUTHORS
Requires-Dist: pyserial==3.5
Requires-Dist: pygeoif==1.4.0
Dynamic: license-file
